falcon_tryton.py
falcon_tryton-0.1.3.dist-info/licenses/LICENSE
falcon_tryton-0.1.3.dist-info/METADATA
falcon_tryton-0.1.3.dist-info/WHEEL
falcon_tryton-0.1.3.dist-info/top_level.txt
falcon_tryton-0.1.3.dist-info/RECORD
