Metadata-Version: 2.4
Name: falcon_tryton
Version: 0.1.3
Summary: Adds Tryton support to Falcon application
Home-page: https://gitlab.com/numaelis/falcon-tryton
Author: Numael Garay
Author-email: mantrixsoft@gmail.com
License: GPL-3
Keywords: falcon tryton web
Platform: any
Classifier: Environment :: Web Environment
Classifier: Framework :: Tryton
Classifier: Intended Audience :: Developers
Classifier: License :: OSI Approved :: GNU General Public License (GPL)
Classifier: Operating System :: OS Independent
Classifier: Programming Language :: Python :: 3
Classifier: Topic :: Internet :: WWW/HTTP :: Dynamic Content
Classifier: Topic :: Software Development :: Libraries :: Python Modules
Requires-Python: >=3.8
License-File: LICENSE
Requires-Dist: Falcon>=4.0
Requires-Dist: Werkzeug
Requires-Dist: trytond>=5.0
Dynamic: author
Dynamic: author-email
Dynamic: classifier
Dynamic: description
Dynamic: description-content-type
Dynamic: home-page
Dynamic: keywords
Dynamic: license
Dynamic: license-file
Dynamic: platform
Dynamic: requires-dist
Dynamic: requires-python
Dynamic: summary
